PythonHeJupyterJiqiXuexiRumenChuyi/README.md
PythonHeJupyterJiqiXuexiRumenChuyi/__init__.py
PythonHeJupyterJiqiXuexiRumenChuyi/__main__.py
PythonHeJupyterJiqiXuexiRumenChuyi/file.epub
PythonHeJupyterJiqiXuexiRumenChuyi/index.html
PythonHeJupyterJiqiXuexiRumenChuyi/css/__init__.py
PythonHeJupyterJiqiXuexiRumenChuyi/css/annotations.css
PythonHeJupyterJiqiXuexiRumenChuyi/css/main.css
PythonHeJupyterJiqiXuexiRumenChuyi/css/normalize.css
PythonHeJupyterJiqiXuexiRumenChuyi/css/popup.css
PythonHeJupyterJiqiXuexiRumenChuyi/font/__init__.py
PythonHeJupyterJiqiXuexiRumenChuyi/font/fontello.eot
PythonHeJupyterJiqiXuexiRumenChuyi/font/fontello.svg
PythonHeJupyterJiqiXuexiRumenChuyi/font/fontello.ttf
PythonHeJupyterJiqiXuexiRumenChuyi/font/fontello.woff
PythonHeJupyterJiqiXuexiRumenChuyi/img/__init__.py
PythonHeJupyterJiqiXuexiRumenChuyi/img/annotator-glyph-sprite.png
PythonHeJupyterJiqiXuexiRumenChuyi/img/annotator-icon-sprite.png
PythonHeJupyterJiqiXuexiRumenChuyi/img/apple-touch-icon.png
PythonHeJupyterJiqiXuexiRumenChuyi/img/cancelfullscreen.png
PythonHeJupyterJiqiXuexiRumenChuyi/img/close.png
PythonHeJupyterJiqiXuexiRumenChuyi/img/fullscreen.png
PythonHeJupyterJiqiXuexiRumenChuyi/img/loader.gif
PythonHeJupyterJiqiXuexiRumenChuyi/img/menu-icon.png
PythonHeJupyterJiqiXuexiRumenChuyi/img/save.png
PythonHeJupyterJiqiXuexiRumenChuyi/img/saved.png
PythonHeJupyterJiqiXuexiRumenChuyi/img/settings-s.png
PythonHeJupyterJiqiXuexiRumenChuyi/img/settings.png
PythonHeJupyterJiqiXuexiRumenChuyi/img/star.png
PythonHeJupyterJiqiXuexiRumenChuyi/js/__init__.py
PythonHeJupyterJiqiXuexiRumenChuyi/js/epub.js
PythonHeJupyterJiqiXuexiRumenChuyi/js/epub.min.js
PythonHeJupyterJiqiXuexiRumenChuyi/js/epub.min.map
PythonHeJupyterJiqiXuexiRumenChuyi/js/hooks.min.js
PythonHeJupyterJiqiXuexiRumenChuyi/js/hooks.min.map
PythonHeJupyterJiqiXuexiRumenChuyi/js/reader.js
PythonHeJupyterJiqiXuexiRumenChuyi/js/reader.js.map
PythonHeJupyterJiqiXuexiRumenChuyi/js/reader.min.js
python_he_jupyter_jiqi_xuexi_rumen_chuyi-2024.3.6.0.dist-info/METADATA
python_he_jupyter_jiqi_xuexi_rumen_chuyi-2024.3.6.0.dist-info/WHEEL
python_he_jupyter_jiqi_xuexi_rumen_chuyi-2024.3.6.0.dist-info/entry_points.txt
python_he_jupyter_jiqi_xuexi_rumen_chuyi-2024.3.6.0.dist-info/top_level.txt
python_he_jupyter_jiqi_xuexi_rumen_chuyi-2024.3.6.0.dist-info/RECORD
